sbml2matlab/__init__.py
sbml2matlab/_sbml2matlab.so
sbml2matlab/sbml2matlab.py
sbml2matlab-1.2.3.1.dist-info/METADATA
sbml2matlab-1.2.3.1.dist-info/WHEEL
sbml2matlab-1.2.3.1.dist-info/top_level.txt
sbml2matlab-1.2.3.1.dist-info/RECORD
