Metadata-Version: 2.1
Name: sbml2matlab
Version: 1.2.3.1
Summary: An SBML to MATLAB translator
Home-page: https://github.com/stanleygu/sbml2matlab
Author: Stanley Gu, Lucian Smith
Author-email: UNKNOWN
License: UNKNOWN
Platform: UNKNOWN
